Metadata-Version: 2.1
Name: aldryn-categories
Version: 1.2.0
Summary: Hierarchical categories/taxonomies for your Django project
Home-page: https://github.com/aldryn/aldryn-categories
Author: Divio AG
Author-email: info@divio.ch
License: BSD License
Platform: OS Independent
Classifier: Development Status :: 5 - Production/Stable
Classifier: Environment :: Web Environment
Classifier: Framework :: Django
Classifier: Framework :: Django :: 1.11
Classifier: Framework :: Django :: 2.0
Classifier: Framework :: Django :: 2.1
Classifier: Intended Audience :: Developers
Classifier: License :: OSI Approved :: BSD License
Classifier: Operating System :: OS Independent
Classifier: Programming Language :: Python
Classifier: Programming Language :: Python :: 2.7
Classifier: Programming Language :: Python :: 3.4
Classifier: Programming Language :: Python :: 3.5
Classifier: Programming Language :: Python :: 3.6
Classifier: Topic :: Internet :: WWW/HTTP :: Dynamic Content
Classifier: Topic :: Software Development
Classifier: Topic :: Software Development :: Libraries
Requires-Dist: django (>=1.11)
Requires-Dist: django-parler
Requires-Dist: django-treebeard
Requires-Dist: aldryn-translation-tools
